setup.py
obj4Alog/__init__.py
obj4Alog/abstract_functions.py
obj4Alog/functions.py
obj4Alog.egg-info/PKG-INFO
obj4Alog.egg-info/SOURCES.txt
obj4Alog.egg-info/dependency_links.txt
obj4Alog.egg-info/requires.txt
obj4Alog.egg-info/top_level.txt